[
  {
    "id": "gg-1784518887786-14-12he85",
    "platform": "google",
    "title": "京东E卡500元 自用送礼皆宜 不记名",
    "price": 98.61,
    "originalPrice": 127.21,
    "commissionRate": 4.97,
    "salesVolume": 9595,
    "rating": 4.94,
    "reviewCount": 16472,
    "category": "点卡充值",
    "imageUrl": "https://picsum.photos/seed/gg14giftcard/400/300",
    "link": "https://shopping.google.com/",
    "shopName": "Google Shopping",
    "isVirtual": true,
    "deliveryType": "digital",
    "meta": {
      "source": "mock"
    },
    "score": 65.81,
    "expectedRevenue": 4.9,
    "aiCopy": "爆款推荐｜点卡充值好物，佣金4.97%，预期收益$4.9",
    "aiTags": [
      "google",
      "点卡充值",
      "热销",
      "精选"
    ],
    "reason": "高佣金+9595销量，转化预期佳",
    "directionId": "points-cards"
  },
  {
    "id": "gg-1784518887786-23-gtex98",
    "platform": "google",
    "title": "中国移动流量包 30GB月包 全国通用",
    "price": 5.71,
    "originalPrice": 7.19,
    "commissionRate": 4.9,
    "salesVolume": 48139,
    "rating": 4.78,
    "reviewCount": 62556,
    "category": "点卡充值",
    "imageUrl": "https://picsum.photos/seed/gg23dataplan/400/300",
    "link": "https://shopping.google.com/",
    "shopName": "Google Shopping",
    "isVirtual": true,
    "deliveryType": "digital",
    "meta": {
      "source": "mock"
    },
    "score": 62.65,
    "expectedRevenue": 0.28,
    "aiCopy": "爆款推荐｜点卡充值好物，佣金4.9%，预期收益$0.28",
    "aiTags": [
      "google",
      "点卡充值",
      "热销",
      "精选"
    ],
    "reason": "高佣金+48139销量，转化预期佳",
    "directionId": "points-cards"
  },
  {
    "id": "gg-1784518887786-8-05mkjm",
    "platform": "google",
    "title": "Q币充值100个 QQ钱包即时到账",
    "price": 22.08,
    "originalPrice": 27.6,
    "commissionRate": 4.51,
    "salesVolume": 24568,
    "rating": 4.78,
    "reviewCount": 42088,
    "category": "点卡充值",
    "imageUrl": "https://picsum.photos/seed/gg8qcoin/400/300",
    "link": "https://shopping.google.com/",
    "shopName": "Google Shopping",
    "isVirtual": true,
    "deliveryType": "digital",
    "meta": {
      "source": "mock"
    },
    "score": 62.64,
    "expectedRevenue": 1,
    "aiCopy": "爆款推荐｜点卡充值好物，佣金4.51%，预期收益$1",
    "aiTags": [
      "google",
      "点卡充值",
      "热销",
      "精选"
    ],
    "reason": "高佣金+24568销量，转化预期佳",
    "directionId": "points-cards"
  },
  {
    "id": "gg-1784518887786-19-wi0khv",
    "platform": "google",
    "title": "婴儿纸尿裤超薄透气 S-XL全码 整箱装",
    "price": 37.31,
    "originalPrice": 42.91,
    "commissionRate": 6.4,
    "salesVolume": 4200,
    "rating": 4.84,
    "reviewCount": 3306,
    "category": "母婴玩具",
    "imageUrl": "https://picsum.photos/seed/gg19babydiapers/400/300",
    "link": "https://shopping.google.com/",
    "shopName": "Google Shopping",
    "isVirtual": false,
    "deliveryType": "physical",
    "meta": {
      "source": "mock"
    },
    "score": 59.55,
    "expectedRevenue": 2.39,
    "aiCopy": "爆款推荐｜母婴玩具好物，佣金6.4%，预期收益$2.39",
    "aiTags": [
      "google",
      "母婴玩具",
      "热销",
      "精选"
    ],
    "reason": "高佣金+4200销量，转化预期佳",
    "directionId": "mother-baby"
  },
  {
    "id": "gg-1784518887786-7-6of167",
    "platform": "google",
    "title": "UI/UX设计师就业班 Figma+作品集",
    "price": 250.78,
    "originalPrice": 323.51,
    "commissionRate": 3,
    "salesVolume": 1041,
    "rating": 4.76,
    "reviewCount": 3270,
    "category": "在线课程",
    "imageUrl": "https://picsum.photos/seed/gg7designcourse/400/300",
    "link": "https://shopping.google.com/",
    "shopName": "Google Shopping",
    "isVirtual": true,
    "deliveryType": "digital",
    "meta": {
      "source": "mock"
    },
    "score": 59.11,
    "expectedRevenue": 7.52,
    "aiCopy": "爆款推荐｜在线课程好物，佣金3%，预期收益$7.52",
    "aiTags": [
      "google",
      "在线课程",
      "热销",
      "精选"
    ],
    "reason": "高佣金+1041销量，转化预期佳",
    "directionId": "online-courses"
  },
  {
    "id": "gg-1784518887786-15-y6twmb",
    "platform": "google",
    "title": "淘宝88VIP年卡 优酷+虾米+饿了么",
    "price": 14.3,
    "originalPrice": 17.3,
    "commissionRate": 5.84,
    "salesVolume": 9202,
    "rating": 4.74,
    "reviewCount": 63803,
    "category": "会员点卡",
    "imageUrl": "https://picsum.photos/seed/gg15vipmembership/400/300",
    "link": "https://shopping.google.com/",
    "shopName": "Google Shopping",
    "isVirtual": true,
    "deliveryType": "digital",
    "meta": {
      "source": "mock"
    },
    "score": 58.59,
    "expectedRevenue": 0.84,
    "aiCopy": "爆款推荐｜会员点卡好物，佣金5.84%，预期收益$0.84",
    "aiTags": [
      "google",
      "会员点卡",
      "热销",
      "精选"
    ],
    "reason": "高佣金+9202销量，转化预期佳",
    "directionId": "membership-cards"
  },
  {
    "id": "gg-1784518887786-0-n6teuf",
    "platform": "google",
    "title": "机械键盘客制化 热插拔 RGB 三模无线",
    "price": 81.04,
    "originalPrice": 98.87,
    "commissionRate": 5.86,
    "salesVolume": 1229,
    "rating": 4.86,
    "reviewCount": 1348,
    "category": "数码电子",
    "imageUrl": "https://picsum.photos/seed/gg0mechanicalkeyboard/400/300",
    "link": "https://shopping.google.com/",
    "shopName": "Google Shopping",
    "isVirtual": false,
    "deliveryType": "physical",
    "meta": {
      "source": "mock"
    },
    "score": 58.14,
    "expectedRevenue": 4.75,
    "aiCopy": "爆款推荐｜数码电子好物，佣金5.86%，预期收益$4.75",
    "aiTags": [
      "google",
      "数码电子",
      "热销",
      "精选"
    ],
    "reason": "高佣金+1229销量，转化预期佳",
    "directionId": "digital-electronics"
  },
  {
    "id": "gg-1784518887786-22-edmj8u",
    "platform": "google",
    "title": "空气炸锅家用无油 5.5L大容量 智能预设菜单",
    "price": 67.17,
    "originalPrice": 76.57,
    "commissionRate": 6.22,
    "salesVolume": 1360,
    "rating": 4.83,
    "reviewCount": 3774,
    "category": "厨房小电",
    "imageUrl": "https://picsum.photos/seed/gg22airfryer/400/300",
    "link": "https://shopping.google.com/",
    "shopName": "Google Shopping",
    "isVirtual": false,
    "deliveryType": "physical",
    "meta": {
      "source": "mock"
    },
    "score": 57.79,
    "expectedRevenue": 4.18,
    "aiCopy": "爆款推荐｜厨房小电好物，佣金6.22%，预期收益$4.18",
    "aiTags": [
      "google",
      "厨房小电",
      "热销",
      "精选"
    ],
    "reason": "高佣金+1360销量，转化预期佳",
    "directionId": "kitchen-appliances"
  },
  {
    "id": "gg-1784518887786-20-i6zs9q",
    "platform": "google",
    "title": "Q币充值100个 QQ钱包即时到账",
    "price": 15.83,
    "originalPrice": 17.41,
    "commissionRate": 5.7,
    "salesVolume": 7717,
    "rating": 4.63,
    "reviewCount": 47996,
    "category": "点卡充值",
    "imageUrl": "https://picsum.photos/seed/gg20qcoin/400/300",
    "link": "https://shopping.google.com/",
    "shopName": "Google Shopping",
    "isVirtual": true,
    "deliveryType": "digital",
    "meta": {
      "source": "mock"
    },
    "score": 57.6,
    "expectedRevenue": 0.9,
    "aiCopy": "爆款推荐｜点卡充值好物，佣金5.7%，预期收益$0.9",
    "aiTags": [
      "google",
      "点卡充值",
      "热销",
      "精选"
    ],
    "reason": "高佣金+7717销量，转化预期佳",
    "directionId": "points-cards"
  },
  {
    "id": "gg-1784518887786-5-3ru8xn",
    "platform": "google",
    "title": "商用字体合集500款 设计师必备版权无忧",
    "price": 28.71,
    "originalPrice": 33.02,
    "commissionRate": 5.53,
    "salesVolume": 4248,
    "rating": 4.7,
    "reviewCount": 11014,
    "category": "数字内容",
    "imageUrl": "https://picsum.photos/seed/gg5fontdesign/400/300",
    "link": "https://shopping.google.com/",
    "shopName": "Google Shopping",
    "isVirtual": true,
    "deliveryType": "digital",
    "meta": {
      "source": "mock"
    },
    "score": 57.49,
    "expectedRevenue": 1.59,
    "aiCopy": "爆款推荐｜数字内容好物，佣金5.53%，预期收益$1.59",
    "aiTags": [
      "google",
      "数字内容",
      "热销",
      "精选"
    ],
    "reason": "高佣金+4248销量，转化预期佳",
    "directionId": "digital-content"
  },
  {
    "id": "gg-1784518887786-9-y21s6v",
    "platform": "google",
    "title": "运动跑步鞋男 透气减震 轻量网面",
    "price": 54.92,
    "originalPrice": 68.65,
    "commissionRate": 4.98,
    "salesVolume": 2809,
    "rating": 4.54,
    "reviewCount": 3922,
    "category": "服饰箱包",
    "imageUrl": "https://picsum.photos/seed/gg9runningshoes/400/300",
    "link": "https://shopping.google.com/",
    "shopName": "Google Shopping",
    "isVirtual": false,
    "deliveryType": "physical",
    "meta": {
      "source": "mock"
    },
    "score": 57.16,
    "expectedRevenue": 2.74,
    "aiCopy": "爆款推荐｜服饰箱包好物，佣金4.98%，预期收益$2.74",
    "aiTags": [
      "google",
      "服饰箱包",
      "热销",
      "精选"
    ],
    "reason": "高佣金+2809销量，转化预期佳",
    "directionId": "sports-fitness"
  },
  {
    "id": "gg-1784518887786-13-qq3hps",
    "platform": "google",
    "title": "坚果零食大礼包 每日坚果 混合装30包",
    "price": 15.2,
    "originalPrice": 18.7,
    "commissionRate": 3.13,
    "salesVolume": 8975,
    "rating": 4.67,
    "reviewCount": 11197,
    "category": "食品保健",
    "imageUrl": "https://picsum.photos/seed/gg13mixednutssnack/400/300",
    "link": "https://shopping.google.com/",
    "shopName": "Google Shopping",
    "isVirtual": false,
    "deliveryType": "physical",
    "meta": {
      "source": "mock"
    },
    "score": 57.02,
    "expectedRevenue": 0.48,
    "aiCopy": "爆款推荐｜食品保健好物，佣金3.13%，预期收益$0.48",
    "aiTags": [
      "google",
      "食品保健",
      "热销",
      "精选"
    ],
    "reason": "高佣金+8975销量，转化预期佳",
    "directionId": "food-health"
  },
  {
    "id": "gg-1784518887786-3-jexe1r",
    "platform": "google",
    "title": "Figma专业版 年订阅 UI设计协作",
    "price": 105.75,
    "originalPrice": 121.61,
    "commissionRate": 3.5,
    "salesVolume": 1047,
    "rating": 4.94,
    "reviewCount": 1642,
    "category": "SaaS服务",
    "imageUrl": "https://picsum.photos/seed/gg3uidesigntool/400/300",
    "link": "https://shopping.google.com/",
    "shopName": "Google Shopping",
    "isVirtual": true,
    "deliveryType": "digital",
    "meta": {
      "source": "mock"
    },
    "score": 56.93,
    "expectedRevenue": 3.7,
    "aiCopy": "爆款推荐｜SaaS服务好物，佣金3.5%，预期收益$3.7",
    "aiTags": [
      "google",
      "SaaS服务",
      "热销",
      "精选"
    ],
    "reason": "高佣金+1047销量，转化预期佳",
    "directionId": "saas-services"
  },
  {
    "id": "gg-1784518887786-10-ksd88c",
    "platform": "google",
    "title": "瑜伽垫加厚防滑 TPE环保 初学者健身",
    "price": 13.83,
    "originalPrice": 16.32,
    "commissionRate": 4.12,
    "salesVolume": 5888,
    "rating": 4.81,
    "reviewCount": 8785,
    "category": "运动户外",
    "imageUrl": "https://picsum.photos/seed/gg10yogamat/400/300",
    "link": "https://shopping.google.com/",
    "shopName": "Google Shopping",
    "isVirtual": false,
    "deliveryType": "physical",
    "meta": {
      "source": "mock"
    },
    "score": 56.56,
    "expectedRevenue": 0.57,
    "aiCopy": "爆款推荐｜运动户外好物，佣金4.12%，预期收益$0.57",
    "aiTags": [
      "google",
      "运动户外",
      "热销",
      "精选"
    ],
    "reason": "高佣金+5888销量，转化预期佳",
    "directionId": "sports-fitness"
  },
  {
    "id": "gg-1784518887786-17-xdk2wq",
    "platform": "google",
    "title": "智能手表运动健康监测 心率血氧 GPS 长续航",
    "price": 90.53,
    "originalPrice": 105.01,
    "commissionRate": 5.09,
    "salesVolume": 1365,
    "rating": 4.48,
    "reviewCount": 1202,
    "category": "数码电子",
    "imageUrl": "https://picsum.photos/seed/gg17smartwatch/400/300",
    "link": "https://shopping.google.com/",
    "shopName": "Google Shopping",
    "isVirtual": false,
    "deliveryType": "physical",
    "meta": {
      "source": "mock"
    },
    "score": 56.47,
    "expectedRevenue": 4.61,
    "aiCopy": "爆款推荐｜数码电子好物，佣金5.09%，预期收益$4.61",
    "aiTags": [
      "google",
      "数码电子",
      "热销",
      "精选"
    ],
    "reason": "高佣金+1365销量，转化预期佳",
    "directionId": "digital-electronics"
  }
]